rosey_keras/__init__.py
rosey_keras/activations.py
rosey_keras/layers.py
rosey_keras/losses.py
rosey_keras/metrics.py
rosey_keras/regularizers.py
rosey_keras-0.20200131.dist-info/METADATA
rosey_keras-0.20200131.dist-info/WHEEL
rosey_keras-0.20200131.dist-info/top_level.txt
rosey_keras-0.20200131.dist-info/RECORD
